README.md
setup.py
src/pyduke/__init__.py
src/pyduke/setup.py
src/pyduke.egg-info/PKG-INFO
src/pyduke.egg-info/SOURCES.txt
src/pyduke.egg-info/dependency_links.txt
src/pyduke.egg-info/not-zip-safe
src/pyduke.egg-info/requires.txt
src/pyduke.egg-info/top_level.txt
src/pyduke/common/__init__.py
src/pyduke/common/core_util.py
src/pyduke/common/data_util.py
src/pyduke/mlutil/__init__.py
src/pyduke/mlutil/data_processor.py