Metadata-Version: 1.0
Name: pyduke
Version: 1.3.1
Summary: Duke python utilities
Home-page: http://github.com/cafeduke/pyduke
Author: Raghunandan Seshadri
Author-email: raghubs81@gmail.com
License: None
Platform: UNKNOWN
